tator/__init__.py
tator/version.py
tator/extractor/__init__.py
tator/extractor/__main__.py
tator/extractor/env_launcher.py
tator/extractor/extractor.py
tator/openapi/__init__.py
tator/openapi/tator_openapi/__init__.py
tator/openapi/tator_openapi/api_client.py
tator/openapi/tator_openapi/configuration.py
tator/openapi/tator_openapi/exceptions.py
tator/openapi/tator_openapi/rest.py
tator/openapi/tator_openapi/api/__init__.py
tator/openapi/tator_openapi/api/tator_api.py
tator/openapi/tator_openapi/models/__init__.py
tator/openapi/tator_openapi/models/affiliation.py
tator/openapi/tator_openapi/models/affiliation_spec.py
tator/openapi/tator_openapi/models/affiliation_update.py
tator/openapi/tator_openapi/models/algorithm.py
tator/openapi/tator_openapi/models/algorithm_manifest.py
tator/openapi/tator_openapi/models/algorithm_manifest_spec.py
tator/openapi/tator_openapi/models/algorithm_parameter.py
tator/openapi/tator_openapi/models/algorithm_spec.py
tator/openapi/tator_openapi/models/announcement.py
tator/openapi/tator_openapi/models/applet.py
tator/openapi/tator_openapi/models/applet_spec.py
tator/openapi/tator_openapi/models/archive_config.py
tator/openapi/tator_openapi/models/attribute_combinator_spec.py
tator/openapi/tator_openapi/models/attribute_filter_spec.py
tator/openapi/tator_openapi/models/attribute_operation_spec.py
tator/openapi/tator_openapi/models/attribute_type.py
tator/openapi/tator_openapi/models/attribute_type_delete.py
tator/openapi/tator_openapi/models/attribute_type_spec.py
tator/openapi/tator_openapi/models/attribute_type_update.py
tator/openapi/tator_openapi/models/attribute_type_update_attribute_type_update.py
tator/openapi/tator_openapi/models/audio_definition.py
tator/openapi/tator_openapi/models/autocomplete_service.py
tator/openapi/tator_openapi/models/auxiliary_file_definition.py
tator/openapi/tator_openapi/models/bad_request_response.py
tator/openapi/tator_openapi/models/bookmark.py
tator/openapi/tator_openapi/models/bookmark_spec.py
tator-1.6.4.dist-info/LICENSE.md
tator-1.6.4.dist-info/METADATA
tator-1.6.4.dist-info/WHEEL
tator-1.6.4.dist-info/top_level.txt
tator-1.6.4.dist-info/RECORD
