Metadata-Version: 2.1
Name: tator
Version: 1.6.4
Summary: Python client for Tator
Home-page: https://github.com/cvisionai/tator-py
Author: CVision AI, Inc.
Author-email: info@cvisionai.com
License: UNKNOWN
Keywords: OpenAPI,OpenAPI-Generator,Tator
Platform: UNKNOWN
License-File: LICENSE.md
Requires-Dist: Pillow>=10.3.0
Requires-Dist: certifi>=14.05.14
Requires-Dist: progressbar2>=3.51.4
Requires-Dist: psutil>=5.9.5
Requires-Dist: python-dateutil>=2.5.3
Requires-Dist: pyyaml>=5.4
Requires-Dist: requests>=2.32.4
Requires-Dist: six>=1.10
Requires-Dist: urllib3>=2.5.0
